securezy/__init__.py
securezy/__main__.py
securezy/cli.py
securezy/paths.py
securezy/plugins/__init__.py
securezy/plugins/hello.py
securezy/tools/__init__.py
securezy/tools/crack.py
securezy/tools/crypto.py
securezy/tools/hashing.py
securezy/tools/headers.py
securezy/tools/jwt.py
securezy/tools/output.py
securezy/tools/password_audit.py
securezy/tools/plugin_scaffold.py
securezy/tools/plugins.py
securezy/tools/portscan.py
securezy/tools/profiles.py
securezy/tools/pwgen.py
securezy/tools/reporting.py
securezy/tools/tls.py
securezy/tools/vault.py
securezy/tools/webhook.py
securezy_cli-0.1.5.dist-info/METADATA
securezy_cli-0.1.5.dist-info/WHEEL
securezy_cli-0.1.5.dist-info/entry_points.txt
securezy_cli-0.1.5.dist-info/licenses/LICENSE
securezy_cli-0.1.5.dist-info/RECORD
