Metadata-Version: 2.4
Name: securezy-cli
Version: 0.1.5
Summary: Lightweight security utility CLI (port scan, vault, crypto, hashing, reports, plugins).
Project-URL: Homepage, https://github.com/akashkokare2910/securezy-cli
Project-URL: Repository, https://github.com/akashkokare2910/securezy-cli
Project-URL: Issues, https://github.com/akashkokare2910/securezy-cli/issues
Author: Akash
License: MIT License
License-File: LICENSE
Keywords: audit,cli,encryption,hashing,network,security
Classifier: Development Status :: 3 - Alpha
Classifier: Environment :: Console
Classifier: License :: OSI Approved :: MIT License
Classifier: Operating System :: OS Independent
Classifier: Programming Language :: Python :: 3
Classifier: Programming Language :: Python :: 3 :: Only
Classifier: Programming Language :: Python :: 3.9
Classifier: Programming Language :: Python :: 3.10
Classifier: Programming Language :: Python :: 3.11
Classifier: Programming Language :: Python :: 3.12
Classifier: Topic :: Security
Requires-Python: >=3.9
Requires-Dist: rich>=13.0.0
Requires-Dist: typer>=0.9.0
Provides-Extra: crypto
Requires-Dist: cryptography>=41.0.0; extra == 'crypto'
Provides-Extra: dev
Requires-Dist: pytest>=7.4.0; extra == 'dev'
Requires-Dist: ruff>=0.3.0; extra == 'dev'
Provides-Extra: vault
Requires-Dist: cryptography>=41.0.0; extra == 'vault'
